{"guid":"root________","title":"","index":0,"dateAdded":1689180457773000,"lastModified":1726069574799000,"id":1,"typeCode":2,"type":"text/x-moz-place-container","root":"placesRoot","children":[{"guid":"menu________","title":"menu","index":0,"dateAdded":1689180457773000,"lastModified":1689180457908000,"id":2,"typeCode":2,"type":"text/x-moz-place-container","root":"bookmarksMenuFolder","children":[{"guid":"dYIqm8dPJLyd","title":"Mozilla Firefox","index":0,"dateAdded":1689180457908000,"lastModified":1689180457908000,"id":7,"typeCode":2,"type":"text/x-moz-place-container","children":[{"guid":"MZG7E5M8Cv1X","title":"Get Help","index":0,"dateAdded":1689180457908000,"lastModified":1689180457908000,"id":8,"typeCode":1,"iconUri":"fake-favicon-uri:https://support.mozilla.org/products/firefox","type":"text/x-moz-place","uri":"https://support.mozilla.org/products/firefox"},{"guid":"eyclCMP1rHRO","title":"Customize Firefox","index":1,"dateAdded":1689180457908000,"lastModified":1689180457908000,"id":9,"typeCode":1,"iconUri":"fake-favicon-uri:https://support.mozilla.org/kb/customize-firefox-controls-buttons-and-toolbars?utm_source=firefox-browser&utm_medium=default-bookmarks&utm_campaign=customize","type":"text/x-moz-place","uri":"https://support.mozilla.org/kb/customize-firefox-controls-buttons-and-toolbars?utm_source=firefox-browser&utm_medium=default-bookmarks&utm_campaign=customize"},{"guid":"8TebK2zgwsNF","title":"Get Involved","index":2,"dateAdded":1689180457908000,"lastModified":1689180457908000,"id":10,"typeCode":1,"iconUri":"fake-favicon-uri:https://www.mozilla.org/contribute/","type":"text/x-moz-place","uri":"https://www.mozilla.org/contribute/"},{"guid":"Ax8Vh6_qfAuu","title":"About Us","index":3,"dateAdded":1689180457908000,"lastModified":1689180457908000,"id":11,"typeCode":1,"iconUri":"fake-favicon-uri:https://www.mozilla.org/about/","type":"text/x-moz-place","uri":"https://www.mozilla.org/about/"}]}]},{"guid":"toolbar_____","title":"toolbar","index":1,"dateAdded":1689180457773000,"lastModified":1726069574799000,"id":3,"typeCode":2,"type":"text/x-moz-place-container","root":"toolbarFolder","children":[{"guid":"r8D1AiAUt3qT","title":"Freshdesk","index":0,"dateAdded":1689180513987000,"lastModified":1724084174116000,"id":13,"typeCode":1,"iconUri":"https://fassetsblue.freshdesk.com/production/a/assets/images/favicon-1b996e2f7cccdd955c536b54851109ee47631440e2173a9e938569cd73f01439.ico","type":"text/x-moz-place","uri":"https://support.aquasec.com/a/dashboard/16000000226"},{"guid":"W3QedSNPPKFF","title":"BIG3","index":1,"dateAdded":1724190016472000,"lastModified":1724190018905000,"id":163,"typeCode":1,"iconUri":"https://fassetsblue.freshdesk.com/production/a/assets/images/favicon-c651f3c77aef46e50dca0d78815a87957836ffe3396eb1edbe7ba3243725918d.ico","type":"text/x-moz-place","uri":"https://support.aquasec.com/a/tickets/filters/search?label=Tickets%20from%20UPS&orderBy=created_at&orderType=desc&q[]=status%3Fis_in%3A%5B0%5D&q[]=company%3Fis_in%3A%5B%2216000372062%22%2C16000369714%2C16000409242%5D&ref=_created"},{"guid":"7m00lW6iI4E-","title":"Confluence","index":2,"dateAdded":1722879085914000,"lastModified":1722879091463000,"id":152,"typeCode":1,"iconUri":"https://wiki-aquasec.atlassian.net/wiki/s/1625236355/6452/dc8749b45947e9573d5fc46da17525cc488407c0/1/_/favicon-update.ico","type":"text/x-moz-place","uri":"https://wiki-aquasec.atlassian.net/wiki/spaces/~7120200dc1f2d9efab4920a65ce2c53a2bdda3/overview"},{"guid":"SmZPCks_AbEY","title":"Opsgenie","index":3,"dateAdded":1693947321360000,"lastModified":1694116808850000,"id":46,"typeCode":1,"iconUri":"https://og-frontend.prod-east.frontend.public.atl-paas.net/assets/favicon.ico","type":"text/x-moz-place","uri":"https://scalock.app.opsgenie.com/alert/list"},{"guid":"9PCZqQ-4lBpk","title":"Jira","index":4,"dateAdded":1689360598884000,"lastModified":1722879095065000,"id":30,"typeCode":1,"iconUri":"https://scalock.atlassian.net/s/-3ddrgv/b/8/b6b48b2829824b869586ac216d119363/_/favicon-family.ico","type":"text/x-moz-place","uri":"https://scalock.atlassian.net/jira/your-work"},{"guid":"d_sqUfBRj6wI","title":"Bitbucket","index":5,"dateAdded":1712083079195000,"lastModified":1716097491630000,"id":92,"typeCode":1,"iconUri":"https://bbc-object-storage--frontbucket.us-east-1.prod.public.atl-paas.net/2a4465150ac3/img/logos/bitbucket/android-chrome-192x192.png","type":"text/x-moz-place","uri":"https://bitbucket.org/search?account=%7B042a28a0-e093-4321-8cd6-8995a50131b4%7D"},{"guid":"xAt9Wdp3UC0P","title":"AQUA","index":6,"dateAdded":1689180571060000,"lastModified":1725986168375000,"id":22,"typeCode":2,"type":"text/x-moz-place-container","children":[{"guid":"f5q5zFhWaCHL","title":"Freshdesk","index":0,"dateAdded":1724084095941000,"lastModified":1724189945337000,"id":160,"typeCode":2,"type":"text/x-moz-place-container","children":[{"guid":"wx9GksdySOtq","title":"Teamboard","index":0,"dateAdded":1721239526963000,"lastModified":1724084164304000,"id":138,"typeCode":1,"iconUri":"https://fassetsblue.freshdesk.com/production/a/assets/images/favicon-1b7cade9d9d62c82e55c358e02acb8e752be2289f8385a2942231fcf7fa521d0.ico","type":"text/x-moz-place","uri":"https://aquasecurity.freshdesk.com/a/dashboard/16000000633"},{"guid":"YAtwQCzo8H_l","title":"CORE KB","index":1,"dateAdded":1720809856823000,"lastModified":1724084199757000,"id":137,"typeCode":1,"iconUri":"https://fassets.freshdesk.com/production/a/assets/images/favicon-8cbb381197009e33ef7ba8799e0cafb3c41f7dc264d8294bb58aaee515c1eae1.ico","type":"text/x-moz-place","uri":"https://support.aquasec.com/a/solutions/categories/16000047926/folders/16000098222?portalId=16000023935"},{"guid":"ZedQ0F6aI2Mt","title":"Idle Report","index":2,"dateAdded":1724084366535000,"lastModified":1724084376417000,"id":161,"typeCode":1,"iconUri":"fake-favicon-uri:https://support.aquasec.com/a/dashboard/16000000226","type":"text/x-moz-place","uri":"https://support.aquasec.com/a/analytics/reports/OTU5Njc5/page/5"}]},{"guid":"LhKxcJI_moFK","title":"Docs","index":1,"dateAdded":1722356354144000,"lastModified":1724084199757000,"id":145,"typeCode":2,"type":"text/x-moz-place-container","children":[{"guid":"xNkOSCpRIW_c","title":"Aqua Docs","index":0,"dateAdded":1689361087467000,"lastModified":1722356357305000,"id":31,"typeCode":1,"iconUri":"https://www.aquasec.com/wp-content/themes/aqua3/favicon.ico","type":"text/x-moz-place","uri":"https://docs.aquasec.com/"},{"guid":"G59_7tEELBvf","title":"Public KB's","index":1,"dateAdded":1689714317935000,"lastModified":1722356358753000,"id":35,"typeCode":1,"iconUri":"https://support.aquasec.com/assets/touch/touch-icon-ipad-retina.png","type":"text/x-moz-place","uri":"https://support.aquasec.com/support/solutions/folders/16000091094"},{"guid":"Yw6CTqKiOgcx","title":"Release Information – Aqua Docs","index":2,"dateAdded":1689180514001000,"lastModified":1722356392166000,"id":19,"typeCode":1,"iconUri":"https://docs.aquasec.com/favicon/favicon.ico","type":"text/x-moz-place","uri":"https://docs.aquasec.com/v2022.4/release-information/"},{"guid":"J_xzHutMqH_0","title":"ConfigMaps and Secrets – Aqua Docs","index":3,"dateAdded":1702919509273000,"lastModified":1722356393774000,"id":58,"typeCode":1,"iconUri":"https://docs.aquasec.com/favicon/favicon.ico","type":"text/x-moz-place","uri":"https://docs.aquasec.com/v2022.4/platform/deployments/deployments-in-classic-mode/deploy-on-kubernetes-and-openshift/deploy-k8s-configmaps-and-secrets/#section-aqua-packaged-database-config-map"}]},{"guid":"iPULjW1DrJ-e","title":"Jira","index":2,"dateAdded":1722356415221000,"lastModified":1722356503739000,"id":146,"typeCode":2,"type":"text/x-moz-place-container","children":[{"guid":"uTNRkmVi0PXs","title":"JIRA = My Pending Support","index":0,"dateAdded":1695752690414000,"lastModified":1722356419777000,"id":50,"typeCode":1,"iconUri":"https://scalock.atlassian.net/s/xtxyma/b/6/b6b48b2829824b869586ac216d119363/_/favicon-family.ico","type":"text/x-moz-place","uri":"https://scalock.atlassian.net/issues/?jql=reporter%20%3D%20712020%3A0dc1f2d9-efab-4920-a65c-e2c53a2bdda3%20AND%20status%20%3D%20%22Pending%20Support%22"},{"guid":"JKpz6mKX-gqq","title":"JIRA != Done","index":1,"dateAdded":1706046717736000,"lastModified":1722356421754000,"id":64,"typeCode":1,"iconUri":"https://scalock.atlassian.net/s/-3ddrgv/b/8/_/favicon-family.ico","type":"text/x-moz-place","uri":"https://scalock.atlassian.net/browse/SLK-77952?jql=reporter%20%3D%20712020%3A0dc1f2d9-efab-4920-a65c-e2c53a2bdda3%20AND%20status%20!%3D%20Done"},{"guid":"_y05w_0dHv1g","title":"NFR Portal (RFE)","index":2,"dateAdded":1709140625194000,"lastModified":1722356431637000,"id":80,"typeCode":1,"iconUri":"https://scalock.atlassian.net/s/tod1zk/b/5/_/favicon-family.ico","type":"text/x-moz-place","uri":"https://scalock.atlassian.net/servicedesk/customer/portal/11/group/45/create/181"},{"guid":"g0BpN2AlSLZv","title":"JIS board - Agile Board - JIRA","index":3,"dateAdded":1717023603443000,"lastModified":1722356447615000,"id":126,"typeCode":1,"iconUri":"https://scalock.atlassian.net/s/-vg1gsr/b/8/b6b48b2829824b869586ac216d119363/_/favicon-family.ico","type":"text/x-moz-place","uri":"https://scalock.atlassian.net/jira/software/projects/JIS/boards/368"},{"guid":"uVtETox7w7V8","title":"Product Initiatives | JIRA","index":4,"dateAdded":1718296156082000,"lastModified":1722356449715000,"id":133,"typeCode":1,"iconUri":"https://scalock.atlassian.net/s/278rlr/b/8/b6b48b2829824b869586ac216d119363/_/favicon-family.ico","type":"text/x-moz-place","uri":"https://scalock.atlassian.net/jira/plans/67/scenarios/67/timeline?vid=317"},{"guid":"iyR0_pRYsxY5","title":"Cerebro - JIRA","index":5,"dateAdded":1717088243936000,"lastModified":1722356451534000,"id":127,"typeCode":1,"iconUri":"https://scalock.atlassian.net/s/-vg1gsr/b/8/b6b48b2829824b869586ac216d119363/_/favicon-family.ico","type":"text/x-moz-place","uri":"https://scalock.atlassian.net/jira/dashboards/10633"},{"guid":"oZpz3qSyExmt","title":"Delivery & Release Status - R&D - R&D - Confluence","index":6,"dateAdded":1717529220212000,"lastModified":1722356453503000,"id":128,"typeCode":1,"iconUri":"https://wiki-aquasec.atlassian.net/wiki/s/-873331882/6452/b93331b30ceee4206d8e3e017bd0b23cab89e6d5/1/_/favicon-update.ico","type":"text/x-moz-place","uri":"https://wiki-aquasec.atlassian.net/wiki/spaces/RD/pages/461733889"},{"guid":"-VaJWeeqivgJ","title":"R&D Competency Matrix - R&D - Confluence","index":7,"dateAdded":1718910790111000,"lastModified":1722356457110000,"id":135,"typeCode":1,"iconUri":"https://wiki-aquasec.atlassian.net/wiki/s/-1773998086/6452/ded1032f98549f9dab20c35ab88ed8ea8cbcdf91/1/_/favicon-update.ico","type":"text/x-moz-place","uri":"https://wiki-aquasec.atlassian.net/wiki/spaces/RD/pages/950206465/R+D+Competency+Matrix"}]},{"guid":"9FlN4NixR1nN","title":"Confluence","index":3,"dateAdded":1722356587659000,"lastModified":1722356951108000,"id":147,"typeCode":2,"type":"text/x-moz-place-container","children":[{"guid":"dKsUbJJ-CpS7","title":"Aqua SaaS API Guide + Scripts - Customer Support - Confluence","index":0,"dateAdded":1722356939252000,"lastModified":1722356951108000,"id":150,"typeCode":1,"iconUri":"fake-favicon-uri:https://wiki-aquasec.atlassian.net/wiki/spaces/Support/pages/116523009/Freshdesk","type":"text/x-moz-place","uri":"https://wiki-aquasec.atlassian.net/wiki/spaces/Support/pages/536313857/Aqua+SaaS+API+Guide+Scripts#PythonScript"},{"guid":"W0ZlQACYCcAP","title":"NA Queue Management - Customer Support - Confluence","index":1,"dateAdded":1721340434142000,"lastModified":1722356594849000,"id":139,"typeCode":1,"iconUri":"https://wiki-aquasec.atlassian.net/wiki/s/-211814391/6452/e766e14ab62e24363444fe0ad68ddfcf6bbf989e/1/_/favicon-update.ico","type":"text/x-moz-place","uri":"https://wiki-aquasec.atlassian.net/wiki/spaces/Support/pages/1000701961/NA+Queue+Management"},{"guid":"WQngVkDKvu0U","title":"XP TABLE","index":2,"dateAdded":1721425586503000,"lastModified":1722356597236000,"id":140,"typeCode":1,"iconUri":"https://fassets.freshdesk.com/production/a/assets/images/favicon-0ca51087dfb69f2b24c4714775fdc6632ee608bdaf7993f748e3ad559b0f23f1.ico","type":"text/x-moz-place","uri":"https://aquasecurity.freshdesk.com/a/analytics/reports/OTU5Njc5/page/10"},{"guid":"g3Nc06SdF-Mf","title":"Technology SME HUB","index":3,"dateAdded":1709147012872000,"lastModified":1722356601535000,"id":81,"typeCode":1,"iconUri":"https://wiki-aquasec.atlassian.net/wiki/s/436752342/6452/087105732172b7f0e50e59c557dfea206465d5d3/1/_/favicon-update.ico","type":"text/x-moz-place","uri":"https://wiki-aquasec.atlassian.net/wiki/spaces/SG/pages/205520991/Technology+SME+HUB"}]},{"guid":"YRXpLHc19N-w","title":"SaaS + Retool","index":4,"dateAdded":1706047060458000,"lastModified":1722357155330000,"id":66,"typeCode":2,"type":"text/x-moz-place-container","children":[{"guid":"fp8XG9FWOUkF","title":"Aqua Platform Overview | Retool","index":0,"dateAdded":1722356636770000,"lastModified":1722356677039000,"id":148,"typeCode":1,"iconUri":"https://retool.cspaas.aquasec.com/favicon.png","type":"text/x-moz-place","uri":"https://retool.cspaas.aquasec.com/apps/e9c9d500-08ee-11ec-99e6-87a17fb45e13/Environment%20Management/Aqua%20Platform%20Overview"},{"guid":"d2vIkAFwlXOq","title":"Aqua Platform Dev us-east-1 | Retool","index":1,"dateAdded":1691689646935000,"lastModified":1706047070025000,"id":38,"typeCode":1,"iconUri":"https://retool.cspaas.aquasec.com/favicon.png","type":"text/x-moz-place","uri":"https://retool.cspaas.aquasec.com/apps/Environment%20Management/Aqua%20Platform%20Dev%20us-east-1"},{"guid":"XC-165VOXZAS","title":"Feature Flags Backoffice | Retool","index":2,"dateAdded":1722356155552000,"lastModified":1722356681989000,"id":144,"typeCode":1,"type":"text/x-moz-place","uri":"https://retool.cspaas.aquasec.com/apps/9a894e40-147d-11ec-97a6-433fde5c8d18/Feature%20Flags%20Backoffice"},{"guid":"NiPllEYebAn0","title":"Agentless Scanning | Retool","index":3,"dateAdded":1710516521411000,"lastModified":1722356685708000,"id":83,"typeCode":1,"iconUri":"https://retool.cspaas.aquasec.com/favicon.png","type":"text/x-moz-place","uri":"https://retool.cspaas.aquasec.com/apps/24d43e34-6f27-11ed-a1b8-63f2512caa32/Volume%20Scanning/Dashboard%20(prod-us-1)?_releaseVersion=1.0.0"},{"guid":"BbeEyJ8M1oMc","title":"cloud.aquasec.com | User Config","index":4,"dateAdded":1691689744920000,"lastModified":1722356715655000,"id":39,"typeCode":1,"iconUri":"https://cloud.aquasec.com/ah/favicon.ico","type":"text/x-moz-place","uri":"https://cloud.aquasec.com/ah/#/cspm/admin/users"},{"guid":"H2SxnlpqAvNG","title":"Auth0 Management | Retool","index":5,"dateAdded":1722357138804000,"lastModified":1722357155330000,"id":151,"typeCode":1,"type":"text/x-moz-place","uri":"https://retool.cspaas.aquasec.com/apps/91bd0d06-e694-11ee-a52e-0399c7b6fa19/Infraops/Auth0%20Management"},{"guid":"RvftuUFgYm9b","title":"EU-1 Cloud","index":6,"dateAdded":1689180659650000,"lastModified":1706047073557000,"id":24,"typeCode":1,"iconUri":"https://eu-1.cloud.aquasec.com/assets/img/icons/favicon.ico","type":"text/x-moz-place","uri":"https://eu-1.cloud.aquasec.com/signin"},{"guid":"lePPMgpF5-qY","title":"Asia-1","index":7,"dateAdded":1689180684966000,"lastModified":1706047074839000,"id":25,"typeCode":1,"iconUri":"https://asia-1.cloud.aquasec.com/assets/img/icons/favicon.ico","type":"text/x-moz-place","uri":"https://asia-1.cloud.aquasec.com/signin?logout=true"},{"guid":"OLLcdZLbfLTN","title":"Asia-2","index":8,"dateAdded":1689180706315000,"lastModified":1706047076092000,"id":26,"typeCode":1,"iconUri":"https://asia-2.cloud.aquasec.com/assets/img/icons/favicon.ico","type":"text/x-moz-place","uri":"https://asia-2.cloud.aquasec.com/signin?logout=true"}]},{"guid":"eyaZt1LJi9RX","title":"Aqua Arch + PS","index":5,"dateAdded":1712338732635000,"lastModified":1724084194899000,"id":93,"typeCode":1,"iconUri":"https://ps.aquasec.com/resources/aqua-favicon-wht.png","type":"text/x-moz-place","uri":"https://ps.aquasec.com/architects/"},{"guid":"dmdDgOo6rGUq","title":"","index":6,"dateAdded":1702919531735000,"lastModified":1702919533913000,"id":59,"typeCode":3,"type":"text/x-moz-place-separator"},{"guid":"DhYyLyDjhz6p","title":"Self-Hosted Minor Releases - Bi-Weekly Status - R&D - Confluence","index":7,"dateAdded":1689180514001000,"lastModified":1706046817022000,"id":20,"typeCode":1,"iconUri":"https://wiki-aquasec.atlassian.net/wiki/s/-1846395510/6452/5c5fe9a949c01ddad1bfb1e0ad6a4d923b56d4f8/1/_/favicon-update.ico","type":"text/x-moz-place","uri":"https://wiki-aquasec.atlassian.net/wiki/spaces/RD/pages/48201875/Self-Hosted+Minor+Releases+-+Bi-Weekly+Status"},{"guid":"ccMSCi6KAp0O","title":"File Transfer Options - Customer Support - Confluence","index":8,"dateAdded":1691089520760000,"lastModified":1725546375999000,"id":36,"typeCode":1,"iconUri":"https://wiki-aquasec.atlassian.net/wiki/s/1238699948/6452/c4fd8688f220479d537f6a0bca23e41d59d1be40/1/_/favicon-update.ico","type":"text/x-moz-place","uri":"https://wiki-aquasec.atlassian.net/wiki/spaces/Support/pages/142901579/File+Transfer+Options"},{"guid":"oRXFVSAp7kkc","title":"aquaftp - Microsoft Azure","index":9,"dateAdded":1695308763435000,"lastModified":1717097446734000,"id":49,"typeCode":1,"iconUri":"https://portal.azure.com/Content/static/MsPortalImpl/Pinning/AppleTouch.png","type":"text/x-moz-place","uri":"https://portal.azure.com/#@aquasec.com/resource/subscriptions/49b47de0-017d-412a-a0a8-b8007bc7e3f9/resourceGroups/prod-acr-rg/providers/Microsoft.Storage/storageAccounts/aquaftp/storagebrowser"},{"guid":"mb5hOiQD8P1v","title":"","index":10,"dateAdded":1702919568549000,"lastModified":1702919571091000,"id":61,"typeCode":3,"type":"text/x-moz-place-separator"},{"guid":"1MmSyX9N_HKc","title":"API Reference – Aqua Docs","index":11,"dateAdded":1722356779979000,"lastModified":1722356785609000,"id":149,"typeCode":1,"iconUri":"https://docs.aquasec.com/favicon/favicon.ico","type":"text/x-moz-place","uri":"https://docs.aquasec.com/saas/api-reference/"},{"guid":"-BYlZtTqKMcr","title":"SCS | API Docs","index":12,"dateAdded":1712340182413000,"lastModified":1713461188675000,"id":94,"typeCode":1,"iconUri":"https://codesec.aquasec.com/scan-results-docs/static/favicon-16x16.png","type":"text/x-moz-place","uri":"https://codesec.aquasec.com/scan-results-docs/static/index.html#/"},{"guid":"O6EaWQBsYYmA","title":"SCS | Aqua Trivy Plugin","index":13,"dateAdded":1713461138950000,"lastModified":1713461191291000,"id":97,"typeCode":1,"type":"text/x-moz-place","uri":"https://hub.docker.com/r/aquasec/aqua-scanner"},{"guid":"cr0AulLZy1O7","title":"Aqua CSPM API · Apiary","index":14,"dateAdded":1707849313221000,"lastModified":1722356606339000,"id":76,"typeCode":1,"iconUri":"https://static.apiary.io/assets/fX9wgjhh.png","type":"text/x-moz-place","uri":"https://aquacspm.docs.apiary.io/#reference/keys/key"},{"guid":"PQiKASojsY0v","title":"","index":15,"dateAdded":1713461182027000,"lastModified":1713461182027000,"id":98,"typeCode":3,"type":"text/x-moz-place-separator"},{"guid":"IDDcAvitVezG","title":"MISC","index":16,"dateAdded":1706047141691000,"lastModified":1722356557522000,"id":68,"typeCode":2,"type":"text/x-moz-place-container","children":[{"guid":"YruITMRNKtQn","title":"Time Converter","index":0,"dateAdded":1689180513987000,"lastModified":1706047152009000,"id":15,"typeCode":1,"type":"text/x-moz-place","uri":"https://www.worldtimebuddy.com/?pl=1&lid=293397,100,5,6,7,8&h=100&hf=1"},{"guid":"LKHppf1k8NY4","title":"My Apps","index":1,"dateAdded":1702058162689000,"lastModified":1706047156144000,"id":55,"typeCode":1,"type":"text/x-moz-place","uri":"https://myapps.microsoft.com/"},{"guid":"DDSNuUKyZA5M","title":"Learner Dashboard","index":2,"dateAdded":1689190114975000,"lastModified":1706047236312000,"id":27,"typeCode":1,"iconUri":"https://d36ai2hkxl16us.cloudfront.net/thoughtindustries/image/upload/a_exif,c_fit,t_ti_favicon_v4/v1/course-uploads/804b7661-4221-42ae-90a5-9dcf89b371f1/l7tpwrto6csk-favicon-32x32.png","type":"text/x-moz-place","uri":"https://aquademy.aquasec.com/learn/dashboard"}]},{"guid":"x-_-8mDKgBWc","title":"HR","index":17,"dateAdded":1689180529825000,"lastModified":1722356555203000,"id":21,"typeCode":2,"type":"text/x-moz-place-container","children":[{"guid":"GoPeRpKTYo-u","title":"TriNet Platform","index":0,"dateAdded":1689180513987000,"lastModified":1689180534246000,"id":18,"typeCode":1,"type":"text/x-moz-place","uri":"https://trinet.hrpassport.com/ui-portal-global/#/app.main.iapp?url=%23%2Fssowidget%2Fexpns&section=Me&menuId=115&external=Y"},{"guid":"aOApkdHVchX7","title":"Expense - Concur","index":1,"dateAdded":1689180513987000,"lastModified":1689180540162000,"id":17,"typeCode":1,"type":"text/x-moz-place","uri":"https://www.concursolutions.com/nui/expense"},{"guid":"vdH4oCmdp_Ea","title":"HiBOb","index":2,"dateAdded":1689180513987000,"lastModified":1689180544145000,"id":16,"typeCode":1,"iconUri":"https://images.hibob.com/favicon/bob.svg","type":"text/x-moz-place","uri":"https://app.hibob.com/home?errorMessage=Invitation%20already%20accepted,%20please%20login"}]},{"guid":"pJ95XbbgHtJX","title":"RBAC Exclude List","index":18,"dateAdded":1725986168375000,"lastModified":1725986168375000,"id":169,"typeCode":1,"iconUri":"https://wiki-aquasec.atlassian.net/wiki/s/942658825/6452/bb9c7cbcbefaec568c9e112629a7d81b09ea4fbf/1/_/favicon-update.ico","type":"text/x-moz-place","uri":"https://wiki-aquasec.atlassian.net/wiki/spaces/Core/pages/1010663555/Exclude+list"}]},{"guid":"p5lnl0GgtmlX","title":"CODE","index":7,"dateAdded":1689359091113000,"lastModified":1724785355652000,"id":29,"typeCode":2,"type":"text/x-moz-place-container","children":[{"guid":"TEFFCmAcJOtv","title":"Github | aqusec (public)","index":0,"dateAdded":1689359082740000,"lastModified":1710773244977000,"id":28,"typeCode":1,"iconUri":"https://github.com/fluidicon.png","type":"text/x-moz-place","uri":"https://github.com/aquasecurity"},{"guid":"FDu7TfK05yq6","title":"Github | aqua-helm (public)","index":1,"dateAdded":1706215229030000,"lastModified":1710773255793000,"id":69,"typeCode":1,"iconUri":"https://github.githubassets.com/favicons/favicon.svg","type":"text/x-moz-place","uri":"https://github.com/aquasecurity/aqua-helm"},{"guid":"XTeyChpp97ZT","title":"","index":2,"dateAdded":1710773209866000,"lastModified":1710773209866000,"id":86,"typeCode":3,"type":"text/x-moz-place-separator"},{"guid":"T4bNQqOyL535","title":"scalock / utils — Bitbucket","index":3,"dateAdded":1721861966942000,"lastModified":1724265359768000,"id":143,"typeCode":1,"iconUri":"https://d301sr5gafysq2.cloudfront.net/b1036ea3eef8/img/logos/bitbucket/android-chrome-192x192.png","type":"text/x-moz-place","uri":"https://bitbucket.org/scalock/utils/src/master/"},{"guid":"2Ac7T5wtPsjp","title":"scalock / server / common / logic / consts.go — Bitbucket","index":4,"dateAdded":1713986705751000,"lastModified":1713987839341000,"id":108,"typeCode":1,"iconUri":"https://d301sr5gafysq2.cloudfront.net/1ccd6c45351c/img/logos/bitbucket/android-chrome-192x192.png","type":"text/x-moz-place","uri":"https://bitbucket.org/scalock/server/src/cfce85d9ddcc0a4e209080b83ddc385ea07b02d2/common/logic/consts.go?at=main#consts.go-430"},{"guid":"kUPL_RB1l6W2","title":"scalock / server / common / datastore / slkdb / db_tables.go — Bitbucket","index":5,"dateAdded":1713550063238000,"lastModified":1713987845420000,"id":99,"typeCode":1,"iconUri":"https://bbc-object-storage--frontbucket.us-east-1.prod.public.atl-paas.net/f671822dc8c9/img/logos/bitbucket/android-chrome-192x192.png","type":"text/x-moz-place","uri":"https://bitbucket.org/scalock/server/src/b05eb913573348b5381ebdab89a64398074bdcf4/common/datastore/slkdb/db_tables.go?at=main#db_tables.go-192"},{"guid":"ebtmnTlzb0CF","title":"scalock / server / common / datastore / slkdb / scalock_upgrades.go — Bitbucket","index":6,"dateAdded":1713907998666000,"lastModified":1713987842357000,"id":107,"typeCode":1,"iconUri":"https://bbc-object-storage--frontbucket.us-east-1.prod.public.atl-paas.net/76e38f79bb9a/img/logos/bitbucket/android-chrome-192x192.png","type":"text/x-moz-place","uri":"https://bitbucket.org/scalock/server/src/b05eb913573348b5381ebdab89a64398074bdcf4/common/datastore/slkdb/scalock_upgrades.go?at=main"},{"guid":"-GqHmzDA5yj6","title":"scalock / server / modules / scanqueue / repository / scanqueue.go — Bitbucket","index":7,"dateAdded":1713819528387000,"lastModified":1724253460515000,"id":105,"typeCode":1,"iconUri":"https://d301sr5gafysq2.cloudfront.net/28002f69de3d/img/logos/bitbucket/android-chrome-192x192.png","type":"text/x-moz-place","uri":"https://bitbucket.org/scalock/server/src/da778f811a2c/modules/scanqueue/repository/scanqueue.go?at=main"},{"guid":"AzCkAuH3SChY","title":"","index":8,"dateAdded":1724265354317000,"lastModified":1724265354317000,"id":165,"typeCode":3,"type":"text/x-moz-place-separator"},{"guid":"x9PXrL6eO8JJ","title":"bitbucket | Rest API","index":9,"dateAdded":1713314460927000,"lastModified":1724265376721000,"id":96,"typeCode":1,"iconUri":"https://bbc-object-storage--frontbucket.us-east-1.prod.public.atl-paas.net/8034477c9582/img/logos/bitbucket/android-chrome-192x192.png","type":"text/x-moz-place","uri":"https://bitbucket.org/scalock/server/src/master/sedockweb/restapi/"},{"guid":"Sk6QoV2EfhBI","title":"scalock / server / sedockweb / restapi / restRoutes.go — Bitbucket","index":10,"dateAdded":1713551394044000,"lastModified":1724265364600000,"id":100,"typeCode":1,"iconUri":"https://bbc-object-storage--frontbucket.us-east-1.prod.public.atl-paas.net/52075f1b6e42/img/logos/bitbucket/android-chrome-192x192.png","type":"text/x-moz-place","uri":"https://bitbucket.org/scalock/server/src/master/sedockweb/restapi/restRoutes.go"},{"guid":"0VynjI0dXpq-","title":"scalock / server / sedockweb / restapi / restRouter.go — Bitbucket","index":11,"dateAdded":1724265343727000,"lastModified":1724265367117000,"id":164,"typeCode":1,"iconUri":"https://d301sr5gafysq2.cloudfront.net/b493bcf896d0/img/logos/bitbucket/android-chrome-192x192.png","type":"text/x-moz-place","uri":"https://bitbucket.org/scalock/server/src/master/sedockweb/restapi/restRouter.go"},{"guid":"D-riCrCght5V","title":"","index":12,"dateAdded":1713987814952000,"lastModified":1713987814952000,"id":109,"typeCode":3,"type":"text/x-moz-place-separator"},{"guid":"KIG_KGfmGI5E","title":"Bitbucket | Console","index":13,"dateAdded":1702502997396000,"lastModified":1724263181227000,"id":56,"typeCode":1,"iconUri":"https://d301sr5gafysq2.cloudfront.net/b493bcf896d0/img/logos/bitbucket/android-chrome-192x192.png","type":"text/x-moz-place","uri":"https://bitbucket.org/scalock/server/src/master/"},{"guid":"mjsq9NyajLT_","title":"BitBucket | Audit","index":14,"dateAdded":1714685418752000,"lastModified":1722881618456000,"id":118,"typeCode":1,"iconUri":"https://d301sr5gafysq2.cloudfront.net/84d38be57a23/img/logos/bitbucket/android-chrome-192x192.png","type":"text/x-moz-place","uri":"https://bitbucket.org/scalock/endpoint/src/d9eee2f374c3ac1ef63938946d405534042fb998/src/lib/core/src/auditreason/auditreason.go?at=main#auditreason.go-348"},{"guid":"Br4kFahX9KQW","title":"","index":15,"dateAdded":1722881612334000,"lastModified":1722881612334000,"id":154,"typeCode":3,"type":"text/x-moz-place-separator"},{"guid":"6XlZRjHbbtdB","title":"Bitbucket | Agent","index":16,"dateAdded":1713314420266000,"lastModified":1722881615044000,"id":95,"typeCode":1,"iconUri":"https://d301sr5gafysq2.cloudfront.net/b1036ea3eef8/img/logos/bitbucket/android-chrome-192x192.png","type":"text/x-moz-place","uri":"https://bitbucket.org/scalock/endpoint/src/main/"},{"guid":"ceQbp0cTIwZ_","title":"BitBucket | kube-enforcer","index":17,"dateAdded":1714409838682000,"lastModified":1714416324793000,"id":115,"typeCode":1,"iconUri":"https://d301sr5gafysq2.cloudfront.net/b1036ea3eef8/img/logos/bitbucket/android-chrome-192x192.png","type":"text/x-moz-place","uri":"https://bitbucket.org/scalock/kube-enforcer/src/main/"},{"guid":"o0TYzEcUGvaq","title":"scalock / kube-enforcer / deployment — Bitbucket","index":18,"dateAdded":1724090175027000,"lastModified":1724090193771000,"id":162,"typeCode":1,"iconUri":"https://bbc-object-storage--frontbucket.us-east-1.prod.public.atl-paas.net/19e939a229ff/img/logos/bitbucket/android-chrome-192x192.png","type":"text/x-moz-place","uri":"https://bitbucket.org/scalock/kube-enforcer/src/27a334be8b11fe65bfe2be9a336b59aa2c765eb1/deployment/?at=main"},{"guid":"gsdg2_q58Cbm","title":"scalock / kube-enforcer / src / grpcclient / handlers / handler.go — Bitbucket","index":19,"dateAdded":1722881602072000,"lastModified":1722881621946000,"id":153,"typeCode":1,"iconUri":"https://bbc-object-storage--frontbucket.us-east-1.prod.public.atl-paas.net/c47e626250f7/img/logos/bitbucket/android-chrome-192x192.png","type":"text/x-moz-place","uri":"https://bitbucket.org/scalock/kube-enforcer/src/ae0cdfb2384781aa2e2f652f28c4cfb9e6404d9e/src/grpcclient/handlers/handler.go?at=main#handler.go-102:103,107,109,111,116:118,128,213,217,222,231,235,273,286,289,291,294,296"},{"guid":"Dy-tscuWAwq3","title":"","index":20,"dateAdded":1722881627133000,"lastModified":1722881627133000,"id":155,"typeCode":3,"type":"text/x-moz-place-separator"},{"guid":"VpQ33t2Hyvau","title":"scalock / cloudsploit-api — Bitbucket","index":21,"dateAdded":1723594102290000,"lastModified":1723594102290000,"id":158,"typeCode":1,"iconUri":"https://bbc-object-storage--frontbucket.us-east-1.prod.public.atl-paas.net/d37e97e08d44/img/logos/bitbucket/android-chrome-192x192.png","type":"text/x-moz-place","uri":"https://bitbucket.org/scalock/cloudsploit-api/src/master/"},{"guid":"i4w9UvyWk4Wl","title":"scalock / cybercenter-client / pkg / client / client.go — Bitbucket","index":22,"dateAdded":1723826954374000,"lastModified":1723826954374000,"id":159,"typeCode":1,"iconUri":"https://bbc-object-storage--frontbucket.us-east-1.prod.public.atl-paas.net/f271b6b575d3/img/logos/bitbucket/android-chrome-192x192.png","type":"text/x-moz-place","uri":"https://bitbucket.org/scalock/cybercenter-client/src/329b8298182603690e70613001198a6c5146f79a/pkg/client/client.go?at=master#client.go-48,105"},{"guid":"DDNZ6uehnr5V","title":"Online JavaScript beautifier","index":23,"dateAdded":1720628035076000,"lastModified":1724785355652000,"id":136,"typeCode":1,"iconUri":"https://beautifier.io/web/favicon.png","type":"text/x-moz-place","uri":"https://beautifier.io/"}]},{"guid":"jgwkZYBzzuTE","title":"NOTES","index":8,"dateAdded":1706047108330000,"lastModified":1724431324841000,"id":67,"typeCode":2,"type":"text/x-moz-place-container","children":[{"guid":"Ci0F2pO3IqNy","title":"Agent modules - R&D - Confluence","index":0,"dateAdded":1713810765572000,"lastModified":1713810827353000,"id":101,"typeCode":1,"iconUri":"fake-favicon-uri:https://wiki-aquasec.atlassian.net/wiki/spaces/Support/pages/116523009/Freshdesk","type":"text/x-moz-place","uri":"https://wiki-aquasec.atlassian.net/wiki/spaces/RD/pages/262733857/Agent+modules"},{"guid":"t7ne6JlEC-tt","title":"Agent Troubleshooting Commands - Quality - Confluence","index":1,"dateAdded":1713811144725000,"lastModified":1713811204970000,"id":104,"typeCode":1,"iconUri":"https://wiki-aquasec.atlassian.net/wiki/s/-822723509/6452/b68115d57d1fea36ac322bf2e87459f566901097/1/_/favicon-update.ico","type":"text/x-moz-place","uri":"https://wiki-aquasec.atlassian.net/wiki/spaces/Quality/pages/700154271/Agent+Troubleshooting+Commands"},{"guid":"ZSIdbFvw-VTs","title":"Aqua Controls and Signatures Tests - Quality - Confluence","index":2,"dateAdded":1713810814460000,"lastModified":1713810829606000,"id":102,"typeCode":1,"iconUri":"https://wiki-aquasec.atlassian.net/wiki/s/979263223/6452/c7855d383ff0411a6c5d2a8090bc0b4e8736b044/1/_/favicon-update.ico","type":"text/x-moz-place","uri":"https://wiki-aquasec.atlassian.net/wiki/spaces/Quality/pages/664797217/Aqua+Controls+and+Signatures+Tests"},{"guid":"at3IbUNcHeEZ","title":"","index":3,"dateAdded":1713810824442000,"lastModified":1713810824442000,"id":103,"typeCode":3,"type":"text/x-moz-place-separator"},{"guid":"mxl-C2NyJSca","title":"kubectl Cheat Sheet | Kubernetes","index":4,"dateAdded":1689708364448000,"lastModified":1706047113553000,"id":33,"typeCode":1,"iconUri":"https://kubernetes.io/images/favicon.png","type":"text/x-moz-place","uri":"https://kubernetes.io/docs/reference/kubectl/cheatsheet/"},{"guid":"BJVieWTLRngD","title":"kubectl Quick Reference | Kubernetes","index":5,"dateAdded":1714408144748000,"lastModified":1714408153595000,"id":114,"typeCode":1,"iconUri":"https://kubernetes.io/images/favicon.png","type":"text/x-moz-place","uri":"https://kubernetes.io/docs/reference/kubectl/quick-reference/#updating-resources"},{"guid":"_8Evxk5I0g0K","title":"Kubectl Reference Docs","index":6,"dateAdded":1689707755751000,"lastModified":1706047175828000,"id":32,"typeCode":1,"iconUri":"https://kubernetes.io/images/favicon.png","type":"text/x-moz-place","uri":"https://kubernetes.io/docs/reference/generated/kubectl/kubectl-commands"},{"guid":"APfdji2jyA7U","title":"Supply Chain Sec","index":7,"dateAdded":1696009625786000,"lastModified":1706047261229000,"id":51,"typeCode":1,"iconUri":"https://fassetsblue.freshdesk.com/production/a/assets/images/favicon-dc2c637bca3090b26c02940e2223d7d75a83c711a8485e8dd7e1d9d8faffec27.ico","type":"text/x-moz-place","uri":"https://support.aquasec.com/a/solutions/articles/16000136296?portalId=16000023935"},{"guid":"XKcf5s0SR9Ph","title":"Tcpdump Cheat Sheet.md · GitHub","index":8,"dateAdded":1693421145692000,"lastModified":1706296238109000,"id":45,"typeCode":1,"iconUri":"https://github.githubassets.com/favicons/favicon.svg","type":"text/x-moz-place","uri":"https://gist.github.com/jforge/27962c52223ea9b8003b22b8189d93fb"},{"guid":"q0FWtBu8wirr","title":"podman/docs/tutorials/socket_activation.md at main · containers/podman · GitHub","index":9,"dateAdded":1704485894177000,"lastModified":1710773199828000,"id":62,"typeCode":1,"iconUri":"https://github.com/fluidicon.png","type":"text/x-moz-place","uri":"https://github.com/containers/podman/blob/main/docs/tutorials/socket_activation.md"},{"guid":"_5T9GXZKrVY6","title":"","index":10,"dateAdded":1710773197075000,"lastModified":1710773197075000,"id":85,"typeCode":3,"type":"text/x-moz-place-separator"},{"guid":"-aWOzLa_3xYP","title":"Runtime controls matrix - March 2023 2.xlsx","index":11,"dateAdded":1710476122456000,"lastModified":1710773152823000,"id":82,"typeCode":1,"iconUri":"https://res-1.cdn.office.net/officeonline/x/s/h63BD80475830AA69__layouts/resources/FavIcon_Excel.ico","type":"text/x-moz-place","uri":"https://aquasecurity-my.sharepoint.com/:x:/g/personal/jack_kitchen_aquasec_com/ET7UCrrdanJKsifyGsuQ3pcBoenI9ZACzwZj2LKjE-IaRQ?wdOrigin=TEAMS-MAGLEV.p2p_ns.rwc&wdExp=TEAMS-TREATMENT&wdhostclicktime=1710450357584&web=1"},{"guid":"5tGFNZxBRyFw","title":"R&D Mapping.xlsx","index":12,"dateAdded":1706043181749000,"lastModified":1710773160305000,"id":63,"typeCode":1,"iconUri":"https://res-1.cdn.office.net/officeonline/x/s/h63BD80475830AA69__layouts/resources/FavIcon_Excel.ico","type":"text/x-moz-place","uri":"https://aquasecurity.sharepoint.com/:x:/s/TechnicalOperations/Ef_2ElDXAOBOkcwzk2RzfAwB3ZzkKkyYkWNUFl7KSK_nHw?e=tOC3O0&ovuser=bc034cf3-566b-41ca-9f24-5dc49474b05e%2Civan.kukushkin%40aquasec.com&isSPOFile=1&clickparams=eyJBcHBOYW1lIjoiVGVhbXMtRGVza3RvcCIsIkFwcFZlcnNpb24iOiIyOC8yMzExMzAyNjIwMiIsIkhhc0ZlZGVyYXRlZFVzZXIiOmZhbHNlfQ%3D%3D"},{"guid":"lZtCN6FN4uh_","title":"Escalation T2 > T3","index":13,"dateAdded":1707245370013000,"lastModified":1710773171202000,"id":73,"typeCode":1,"iconUri":"https://wiki-aquasec.atlassian.net/wiki/s/633880739/6452/98fae344e2a620203f1e11afea8e7cd3fc5dab8e/1/_/favicon-update.ico","type":"text/x-moz-place","uri":"https://wiki-aquasec.atlassian.net/wiki/spaces/Support/pages/663192320/Escalation+Process+between+Tiers"},{"guid":"WhTDToyq3r-8","title":"SupportMatrix.xlsx","index":14,"dateAdded":1707848012744000,"lastModified":1710773188904000,"id":75,"typeCode":1,"type":"text/x-moz-place","uri":"https://aquasecurity.sharepoint.com/:x:/r/sites/QA-General/_layouts/15/doc2.aspx?sourcedoc=%7BAC3AE9C9-5E5A-430B-BA98-339FBCAEBB62%7D&file=SupportMatrix.xlsx&action=default&mobileredirect=true&cid=2E00AF8F-EB54-411C-9F6D-1C235C838A06&params=eyJBcHBOYW1lIjoiVGVhbXMtRGVza3RvcCIsIkFwcFZlcnNpb24iOiIyOC8yMjA1MDEwMTAwOSJ9&isSPOFile=1&clickparams=eyJBcHBOYW1lIjoiVGVhbXMtRGVza3RvcCIsIkFwcFZlcnNpb24iOiIyOC8yNDAxMDQxNzUwMyIsIkhhc0ZlZGVyYXRlZFVzZXIiOmZhbHNlfQ%3D%3D"},{"guid":"p3yGTUgJdxCP","title":"scalock / server / common / datastore / slkdb / dbs.go — Bitbucket","index":15,"dateAdded":1713819687126000,"lastModified":1713819687126000,"id":106,"typeCode":1,"iconUri":"https://d301sr5gafysq2.cloudfront.net/3adb829cf30d/img/logos/bitbucket/android-chrome-192x192.png","type":"text/x-moz-place","uri":"https://bitbucket.org/scalock/server/src/da778f811a2c457aea31c298561ad8934a61e062/common/datastore/slkdb/dbs.go?at=main#dbs.go-442,463"},{"guid":"uNIeCNhqi4cl","title":"","index":16,"dateAdded":1714141720908000,"lastModified":1714141720908000,"id":113,"typeCode":3,"type":"text/x-moz-place-separator"},{"guid":"43YiFI6apZ_w","title":"Linux Hardware Reviews & Performance Benchmarks, Open-Source News - Phoronix","index":17,"dateAdded":1714069013096000,"lastModified":1714069013096000,"id":110,"typeCode":1,"iconUri":"https://www.phoronix.com/android-chrome-192x192.png","type":"text/x-moz-place","uri":"https://www.phoronix.com/"},{"guid":"Y43kpJvhR5rC","title":"Releases · Azure/AKS","index":18,"dateAdded":1714069236661000,"lastModified":1714069236661000,"id":111,"typeCode":1,"iconUri":"https://github.com/fluidicon.png","type":"text/x-moz-place","uri":"https://github.com/Azure/AKS/releases"},{"guid":"oz35YkoBKtMh","title":"Announcements | AWS News Blog","index":19,"dateAdded":1714069270842000,"lastModified":1714069270842000,"id":112,"typeCode":1,"iconUri":"https://a0.awsstatic.com/main/images/site/touch-icon-ipad-144-smile.png","type":"text/x-moz-place","uri":"https://aws.amazon.com/blogs/aws/category/post-types/announcements/"},{"guid":"zzcK6rj5pSFC","title":"Sources of Images for Scanning – Aqua Docs","index":20,"dateAdded":1714413587109000,"lastModified":1714413587109000,"id":116,"typeCode":1,"iconUri":"https://docs.aquasec.com/favicon/favicon.ico","type":"text/x-moz-place","uri":"https://docs.aquasec.com/saas/image-and-function-scanning/image-scanning/sources-of-images-for-scanning/#host-images"},{"guid":"Ckn2ujuyF6Am","title":"Automated-setup Lightning Mode - CS Architects - Confluence","index":21,"dateAdded":1714585502063000,"lastModified":1714585502063000,"id":117,"typeCode":1,"iconUri":"fake-favicon-uri:https://wiki-aquasec.atlassian.net/wiki/spaces/Support/pages/116523009/Freshdesk","type":"text/x-moz-place","uri":"https://wiki-aquasec.atlassian.net/wiki/spaces/CA/pages/828801063/Automated-setup+Lightning+Mode"},{"guid":"fZmRTrR48Gvt","title":"K3s - Lightweight Kubernetes | K3s","index":22,"dateAdded":1715619384867000,"lastModified":1715619384867000,"id":122,"typeCode":1,"iconUri":"https://docs.k3s.io/img/favicon.ico","type":"text/x-moz-place","uri":"https://docs.k3s.io/"},{"guid":"XDGDS7D_fUzM","title":"API Reference","index":23,"dateAdded":1715813087290000,"lastModified":1715813087290000,"id":123,"typeCode":1,"iconUri":"https://www.sublimetext.com/images/icon.png","type":"text/x-moz-place","uri":"https://www.sublimetext.com/docs/api_reference.html#sublime.Syntax"},{"guid":"1R775y2wGLku","title":"inotify(7) - Linux manual page","index":24,"dateAdded":1716483787702000,"lastModified":1716483794492000,"id":124,"typeCode":1,"type":"text/x-moz-place","uri":"https://man7.org/linux/man-pages/man7/inotify.7.html"},{"guid":"cCe6wf9irNO5","title":"Course: Certified Kubernetes Administrator (CKA) with Practice Tests | Udemy","index":25,"dateAdded":1718242173099000,"lastModified":1718242173099000,"id":132,"typeCode":1,"iconUri":"https://www.udemy.com/staticx/udemy/images/v7/apple-touch-icon.png","type":"text/x-moz-place","uri":"https://www.udemy.com/course/certified-kubernetes-administrator-with-practice-tests/learn/lecture/24458474?start=0#overview"},{"guid":"1r2Jdjmixaqf","title":"Full Emoji List, v15.1","index":26,"dateAdded":1721858262606000,"lastModified":1721858262606000,"id":141,"typeCode":1,"type":"text/x-moz-place","uri":"https://unicode.org/emoji/charts/full-emoji-list.html"},{"guid":"xvnXeCFzoddb","title":"Emoji unicode characters for use on the web","index":27,"dateAdded":1721858289759000,"lastModified":1721858289759000,"id":142,"typeCode":1,"iconUri":"https://de9xxjhuq2c2j.cloudfront.net/apps/live-20231204-1/images/twerminal_normal.png","type":"text/x-moz-place","uri":"https://apps.timwhitlock.info/emoji/tables/unicode"},{"guid":"MpO-2GkqB-1M","title":"Radio Garden – Searcy AR","index":28,"dateAdded":1723480450333000,"lastModified":1723480450333000,"id":156,"typeCode":1,"iconUri":"https://radio.garden/public/icons/ios/ios-appicon-180-180.png","type":"text/x-moz-place","uri":"http://radio.garden/visit/searcy-ar/AcsGgG0W"},{"guid":"wVhREPv3hUhh","title":"Core concepts, architecture and lifecycle | gRPC","index":29,"dateAdded":1723568057204000,"lastModified":1723568057204000,"id":157,"typeCode":1,"iconUri":"https://grpc.io/favicons/android-chrome-512x512.png","type":"text/x-moz-place","uri":"https://grpc.io/docs/what-is-grpc/core-concepts/"},{"guid":"V-7AbjcreY0x","title":"Operating Systems: Threads","index":30,"dateAdded":1724270004028000,"lastModified":1724270004028000,"id":166,"typeCode":1,"type":"text/x-moz-place","uri":"https://www.cs.uic.edu/~jbell/CourseNotes/OperatingSystems/4_Threads.html"},{"guid":"wBx_oFO03FmL","title":"bind","index":31,"dateAdded":1724431324841000,"lastModified":1724431324841000,"id":167,"typeCode":1,"iconUri":"https://github.githubassets.com/favicons/favicon.svg","type":"text/x-moz-place","uri":"https://github.com/aquasecurity/aqua-helm/blob/2022.4/kube-enforcer/templates/kube-enforcer-deployment.yaml"}]},{"guid":"s49zQf_FG5dM","title":"LAB","index":9,"dateAdded":1693408883336000,"lastModified":1726069574799000,"id":42,"typeCode":2,"type":"text/x-moz-place-container","children":[{"guid":"0VLAhRCLwrZD","title":"esxi.landilab.com","index":0,"dateAdded":1693408903503000,"lastModified":1718138842602000,"id":43,"typeCode":1,"iconUri":"https://192.168.1.36/ui/apple-touch-icon.png","type":"text/x-moz-place","uri":"https://192.168.1.36/ui/"},{"guid":"OhHMte6mmmWa","title":"pfsense.landilab.com","index":1,"dateAdded":1716938048423000,"lastModified":1718138852707000,"id":125,"typeCode":1,"iconUri":"http://10.99.0.254/apple-touch/apple-touch-icon-ipad-retina-152x152-precomposed.png","type":"text/x-moz-place","uri":"http://10.99.0.254/"},{"guid":"2igcrxtUQqRD","title":"","index":2,"dateAdded":1718138834309000,"lastModified":1718138881935000,"id":130,"typeCode":3,"type":"text/x-moz-place-separator"},{"guid":"uxY0X2CfAjTu","title":"k3s.landilab.com | Rocky UI @ 9090","index":3,"dateAdded":1715614697508000,"lastModified":1726069574799000,"id":119,"typeCode":1,"type":"text/x-moz-place","uri":"https://10.99.0.203:9090/"},{"guid":"0lCiaaR9FtCP","title":"labrat.landilab.com | Rocky UI @ 9090","index":4,"dateAdded":1715619106138000,"lastModified":1715619124057000,"id":121,"typeCode":1,"type":"text/x-moz-place","uri":"https://10.99.0.204:9090/system"},{"guid":"CnzORYatdHHe","title":"Rancher | cowpoke.landilab.com","index":5,"dateAdded":1715616329735000,"lastModified":1718138889798000,"id":120,"typeCode":1,"type":"text/x-moz-place","uri":"https://cowpoke.landilab.com/dashboard/home"},{"guid":"nxfS7FbtURqE","title":"GitLab | labrat.landilab.com:3330","index":6,"dateAdded":1718142513518000,"lastModified":1718142520329000,"id":131,"typeCode":1,"iconUri":"http://gitlab.landilab.com:3330/assets/apple-touch-icon-b049d4bc0dd9626f31db825d61880737befc7835982586d015bded10b4435460.png","type":"text/x-moz-place","uri":"http://gitlab.landilab.com:3330/users/sign_in"},{"guid":"S5dzOTpc-yoc","title":"Aqua 2022.4 | k3s.landilab.com:8080","index":7,"dateAdded":1718314208123000,"lastModified":1718318879567000,"id":134,"typeCode":1,"iconUri":"http://k3s.landilab.com:8080/ico/favicon.ico","type":"text/x-moz-place","uri":"http://k3s.landilab.com:8080/#/login"},{"guid":"npvoDesjFOke","title":"pgAdmin4 | labrat.landilab.com:5050","index":8,"dateAdded":1718138811109000,"lastModified":1718318877154000,"id":129,"typeCode":1,"iconUri":"http://labrat.landilab.com:5050/favicon.ico?ver=80800","type":"text/x-moz-place","uri":"http://labrat.landilab.com:5050/browser/"},{"guid":"uuvOrhBq70Fo","title":"","index":9,"dateAdded":1710779111036000,"lastModified":1710779111036000,"id":87,"typeCode":3,"type":"text/x-moz-place-separator"},{"guid":"f_0jW4HQ4tTt","title":"Polaris Portal","index":10,"dateAdded":1701111977583000,"lastModified":1714151399229000,"id":53,"typeCode":1,"iconUri":"https://retool.cspaas.aquasec.com/favicon.png","type":"text/x-moz-place","uri":"https://retool.cspaas.aquasec.com/apps/9d4e661a-be23-11ec-b433-5379915d73e6/Infraops/Polaris?_releaseVersion=latest"},{"guid":"lcbzhreftZYn","title":"Aqua 2022.4  |  Sandal.tech","index":11,"dateAdded":1708625918779000,"lastModified":1718138898415000,"id":77,"typeCode":1,"iconUri":"https://aqua.k8s.sandal.tech/ico/favicon.ico","type":"text/x-moz-place","uri":"https://aqua.k8s.sandal.tech/"},{"guid":"Dy-eIsPmLR9J","title":"Exploit Database - Exploits for Penetration Testers, Researchers, and Ethical Hackers","index":12,"dateAdded":1725638215284000,"lastModified":1725638215284000,"id":168,"typeCode":1,"type":"text/x-moz-place","uri":"https://www.exploit-db.com/"}]}]},{"guid":"unfiled_____","title":"unfiled","index":3,"dateAdded":1689180457773000,"lastModified":1696009647268000,"id":5,"typeCode":2,"type":"text/x-moz-place-container","root":"unfiledBookmarksFolder"},{"guid":"mobile______","title":"mobile","index":4,"dateAdded":1689180457789000,"lastModified":1689180457904000,"id":6,"typeCode":2,"type":"text/x-moz-place-container","root":"mobileFolder"}]}